[{"Exp":20000,"CommandIds":[2403,2404,2405,2406,2407,2408,2410,2411,2412,2413,2414,2417,2418,2421,2422,2423,2424,2425,2426,2427,2428],"CopyIds":null,"Id":1},{"Id":2,"Exp":80000,"CommandIds":null,"CopyIds":null},{"Id":3,"Exp":200000,"CommandIds":null,"CopyIds":null},{"Id":4,"Exp":500000,"CommandIds":null,"CopyIds":null},{"Id":5,"Exp":1000000,"CommandIds":null,"CopyIds":null},{"Id":6,"Exp":2000000,"CommandIds":null,"CopyIds":null},{"Id":7,"Exp":4000000,"CommandIds":null,"CopyIds":null},{"Id":8,"Exp":8000000,"CommandIds":null,"CopyIds":null},{"Id":9,"Exp":16000000,"CommandIds":null,"CopyIds":null},{"Id":10,"Exp":32000000,"CommandIds":null,"CopyIds":null},{"Id":0,"Exp":0,"CommandIds":null,"CopyIds":null},{"Id":0,"Exp":0,"CommandIds":null,"CopyIds":null},{"Id":0,"Exp":0,"CommandIds":null,"CopyIds":null}]